Workbook

Sheet Profit and loss
A1: Funmi's Kitchen
A2: Profit and loss statement: October 2026, with September 2026 for comparison
A3: All amounts in US dollars. Figures are fictional.
B5: October 2026 | C5: September 2026 | D5: Change | E5: Notes
A6: REVENUE
A7: Bread and pastry sales | B7: 21400 | C7: 19800 | D7: =B7-C7 -> 1600
A8: Cake orders | B8: 6200 | C8: 5100 | D8: =B8-C8 -> 1100 | E8: Halloween cakes in late October
A9: Catering | B9: 7722 | C9: 5523 | D9: =B9-C9 -> 2199 | E9: Matches the catering orders spreadsheet
A10: Coffee and drinks | B10: 2900 | C10: 2750 | D10: =B10-C10 -> 150
A11: Total revenue | B11: =SUM(B7:B10) -> 38222 | C11: =SUM(C7:C10) -> 33173 | D11: =B11-C11 -> 5049
A13: COST OF GOODS SOLD
A14: Ingredients | B14: 10950 | C14: 9880 | D14: =B14-C14 -> 1070 | E14: Butter and flour prices up
A15: Packaging | B15: 1120 | C15: 1010 | D15: =B15-C15 -> 110
A16: Total cost of goods sold | B16: =SUM(B14:B15) -> 12070 | C16: =SUM(C14:C15) -> 10890 | D16: =B16-C16 -> 1180
A18: GROSS PROFIT | B18: =B11-B16 -> 26152 | C18: =C11-C16 -> 22283 | D18: =B18-C18 -> 3869
A19: Gross margin (gross profit / revenue) | B19: =B18/B11 -> 0.68421328 | C19: =C18/C11 -> 0.67172098 | D19: =B19-C19 -> 0.012492302
A21: OPERATING EXPENSES
A22: Wages (2 part-time staff and Funmi) | B22: 11600 | C22: 11200 | D22: =B22-C22 -> 400
A23: Rent | B23: 3200 | C23: 3200 | D23: =B23-C23 -> 0
A24: Utilities | B24: 1450 | C24: 1180 | D24: =B24-C24 -> 270 | E24: Ovens on longer, and heating started
A25: Equipment and repairs | B25: 2350 | C25: 150 | D25: =B25-C25 -> 2200 | E25: Deck oven repair, October 14
A26: Marketing | B26: 300 | C26: 300 | D26: =B26-C26 -> 0
A27: Insurance | B27: 420 | C27: 420 | D27: =B27-C27 -> 0
A28: Card processing fees | B28: 690 | C28: 640 | D28: =B28-C28 -> 50
A29: Van and fuel | B29: 510 | C29: 430 | D29: =B29-C29 -> 80
A30: Other | B30: 260 | C30: 240 | D30: =B30-C30 -> 20
A31: Total operating expenses | B31: =SUM(B22:B30) -> 20780 | C31: =SUM(C22:C30) -> 17760 | D31: =B31-C31 -> 3020
A33: NET PROFIT | B33: =B18-B31 -> 5372 | C33: =C18-C31 -> 4523 | D33: =B33-C33 -> 849
A34: Net margin (net profit / revenue) | B34: =B33/B11 -> 0.14054733 | C34: =C33/C11 -> 0.13634582 | D34: =B34-C34 -> 0.0042015054

Sheet Questions
A1: Three questions about the October 2026 statement
A2: Answer them on your own, using only the Profit and loss sheet. Type your answers in the yellow cells. Then compare them with the Answer key sheet.
A4: 1 | B4: What was the gross profit in October, and what was the gross margin as a percentage of revenue?
A7: 2 | B7: Which single operating expense was the largest in October, and roughly what share of total revenue was it?
A10: 3 | B10: Total revenue rose by about US$5,000 from September to October. Why did net profit rise by much less? Name the two biggest reasons.

Sheet Answer key
A1: Answer key
A2: Values are calculated from the Profit and loss sheet.
A4: Q | B4: Item | C4: Value | D4: Explanation
A5: 1 | B5: Gross profit, October | C5: ='Profit and loss'!B18 -> 26152 | D5: Total revenue minus cost of goods sold (ingredients and packaging).
B6: Gross margin, October | C6: ='Profit and loss'!B19 -> 0.68421328 | D6: Gross profit divided by total revenue. About 68 cents of every dollar is left after ingredients and packaging.
A7: 2 | B7: Largest operating expense: wages | C7: ='Profit and loss'!B22 -> 11600 | D7: Wages are the largest single operating expense.
B8: Wages as a share of revenue | C8: ='Profit and loss'!B22/'Profit and loss'!B11 -> 0.30349014 | D8: Roughly 30 cents of every dollar of revenue goes on wages.
A9: 3 | B9: Change in total revenue | C9: ='Profit and loss'!D11 -> 5049 | D9: Revenue rose, mostly from catering and cakes.
B10: Change in net profit | C10: ='Profit and loss'!D33 -> 849 | D10: Net profit rose by much less than revenue.
B11: Reason 1: equipment and repairs went up by | C11: ='Profit and loss'!D25 -> 2200 | D11: The deck oven repair on October 14 was a one-off cost.
B12: Reason 2: cost of goods sold went up by | C12: ='Profit and loss'!D16 -> 1180 | D12: More sales need more ingredients, and butter and flour prices rose.
B13: Other increases in operating expenses | C13: ='Profit and loss'!D31-'Profit and loss'!D25 -> 820 | D13: Wages, utilities, card fees, fuel, and other costs rose a little too.
